{"single_row_table_data":{"SecondsPlayed":1305.0,"Minutes":22,"PlusMinus":-2,"OffPoss":41,"DefPoss":41,"PenaltyOffPoss":12,"PenaltyDefPoss":4,"SecondChanceOffPoss":4,"TotalPoss":82,"AtRimFGM":8,"AtRimFGA":13,"SecondChanceAtRimFGM":1,"SecondChanceAtRimFGA":1,"PenaltyAtRimFGM":3,"PenaltyAtRimFGA":4,"ShortMidRangeFGM":1,"ShortMidRangeFGA":3,"LongMidRangeFGM":9,"LongMidRangeFGA":13,"Corner3FGM":1,"Corner3FGA":2,"Arc3FGM":1,"Arc3FGA":3,"FG2M":18,"FG2A":29,"FG3M":2,"FG3A":5,"FtPoints":13,"Points":55,"OpponentPoints":57,"SecondChanceFG2M":2,"SecondChanceFG2A":2,"SecondChanceFtPoints":3,"SecondChancePoints":7,"PenaltyFG2M":4,"PenaltyFG2A":8,"PenaltyFtPoints":7,"PenaltyPoints":15,"PtsAssisted2s":28,"PtsUnassisted2s":8,"PtsAssisted3s":6,"PtsPutbacks":2,"NonHeaveArc3FGA":3,"NonHeaveArc3FGM":1,"Fg2aBlocked":1,"Fg3aBlocked":1,"TwoPtAssists":14,"ThreePtAssists":2,"Assists":16,"Arc3Assists":1,"Corner3Assists":1,"AtRimAssists":6,"LongMidRangeAssists":8,"AssistPoints":34,"OffThreePtRebounds":1,"OffTwoPtRebounds":3,"DefTwoPtRebounds":12,"DefRebounds":12,"OffRebounds":4,"Rebounds":16,"Steals":2,"LostBallSteals":2,"LiveBallTurnovers":1,"BadPassOutOfBoundsTurnovers":1,"BadPassTurnovers":1,"DeadBallTurnovers":3,"Turnovers":4,"PenaltyTurnovers":1,"ShootingFouls":4,"Fouls":12,"Loose Ball Fouls":1,"Offensive Fouls":1,"FoulsDrawn":8,"Loose Ball Fouls Drawn":1,"FTA":17,"Technical Free Throw Trips":2,"TwoPtShootingFoulsDrawn":4,"ThreePtShootingFoulsDrawn":1,"NonShootingFoulsDrawn":2,"Blocked2s":1,"BlockedAtRim":1,"Blocks":1,"FirstChancePoints":48,"PenaltyPointsExcludingTakeFouls":15,"PenaltyOffPossExcludingTakeFouls":12,"NonShootingPenaltyNonTakeFouls":1,"NonShootingPenaltyNonTakeFoulsDrawn":2,"Assisted2sPct":0.7777777777777778,"NonPutbacksAssisted2sPct":0.8235294117647058,"Assisted3sPct":1.0,"Fg3Pct":0.4,"NonHeaveFg3Pct":0.4,"Fg2Pct":0.6206896551724138,"SecondChanceFg2Pct":1.0,"PenaltyFg2Pct":0.5,"EfgPct":0.6176470588235294,"SecondChanceEfgPct":1.0,"PenaltyEfgPct":0.5,"TsPct":0.6463414634146342,"SecondChanceTsPct":0.875,"PenaltyTsPct":0.5833333333333334,"FG3APct":0.14705882352941177,"FG3APctBlocked":0.2,"FG2APctBlocked":0.034482758620689655,"AtRimPctBlocked":0.07692307692307693,"Corner3PctBlocked":0.5,"LiveBallTurnoverPct":0.25,"DefTwoPtReboundPct":0.75,"OffTwoPtReboundPct":0.2727272727272727,"OffThreePtReboundPct":0.3333333333333333,"DefFGReboundPct":0.75,"OffFGReboundPct":0.2857142857142857,"OffAtRimReboundPct":0.2,"OffShortMidRangeReboundPct":0.5,"OffLongMidRangeReboundPct":0.25,"OffArc3ReboundPct":0.5,"DefAtRimReboundPct":0.5,"DefShortMidRangeReboundPct":0.8333333333333334,"DefLongMidRangeReboundPct":0.8333333333333334,"Pace":90.48275862068965,"SecondsPerPossOff":14.292682926829269,"SecondsPerPossDef":17.536585365853657,"SecondsExcludingORebsPerPossOff":13.853658536585366,"SecondsExcludingORebsPerPossDef":17.195121951219512,"AtRimFrequency":0.38235294117647056,"AtRimAccuracy":0.6153846153846154,"UnblockedAtRimAccuracy":0.6666666666666666,"AtRimPctAssisted":0.75,"ShortMidRangeFrequency":0.08823529411764706,"ShortMidRangeAccuracy":0.3333333333333333,"UnblockedShortMidRangeAccuracy":0.3333333333333333,"LongMidRangeFrequency":0.38235294117647056,"LongMidRangeAccuracy":0.6923076923076923,"UnblockedLongMidRangeAccuracy":0.6923076923076923,"LongMidRangePctAssisted":0.8888888888888888,"Corner3Frequency":0.058823529411764705,"Corner3Accuracy":0.5,"UnblockedCorner3Accuracy":1.0,"Corner3PctAssisted":1.0,"Arc3Frequency":0.08823529411764706,"Arc3Accuracy":0.3333333333333333,"UnblockedArc3Accuracy":0.3333333333333333,"Arc3PctAssisted":1.0,"SecondChanceAtRimFrequency":0.5,"SecondChanceAtRimAccuracy":1.0,"PenaltyAtRimFrequency":0.5,"PenaltyAtRimAccuracy":0.75,"AtRimFG3AFrequency":0.5294117647058824,"NonHeaveArc3Accuracy":0.3333333333333333,"ShotQualityAvg":0.4981676470588235,"SecondChanceShotQualityAvg":0.4949,"PenaltyShotQualityAvg":0.488,"ShootingFoulsDrawnPct":0.1282051282051282,"TwoPtShootingFoulsDrawnPct":0.12121212121212122,"ThreePtShootingFoulsDrawnPct":0.16666666666666666,"SecondChancePointsPct":0.12727272727272726,"PenaltyPointsPct":0.2727272727272727,"Avg2ptShotDistance":8.958620689655174,"Avg3ptShotDistance":25.619999999999997,"PenaltyOffPossPct":0.2926829268292683},"multi_row_table_data":[{"EntityId":"101112-201609-2405-255-959","TeamId":"1610612756","Name":"Channing Frye, Goran Dragic, Amar'e Stoudemire, Grant Hill, Steve Nash","ShortName":"Frye, Dragic, Stoudemire, Hill, Nash","RowId":"101112-201609-2405-255-959","TeamAbbreviation":"PHX","SecondsPlayed":46.0,"GamesPlayed":1,"Minutes":1,"PlusMinus":1,"OffPoss":2,"DefPoss":2,"PenaltyOffPoss":2,"PenaltyDefPoss":2,"TotalPoss":4,"AtRimFGM":1,"AtRimFGA":1,"PenaltyAtRimFGM":1,"PenaltyAtRimFGA":1,"FG2M":1,"FG2A":1,"FtPoints":2,"Points":4,"OpponentPoints":3,"PenaltyFG2M":1,"PenaltyFG2A":1,"PenaltyFtPoints":2,"PenaltyPoints":4,"PtsAssisted2s":2,"TwoPtAssists":1,"Assists":1,"AtRimAssists":1,"AssistPoints":2,"ShootingFouls":1,"Fouls":1,"FoulsDrawn":1,"FTA":3,"ThreePtShootingFoulsDrawn":1,"FirstChancePoints":4,"PenaltyPointsExcludingTakeFouls":4,"PenaltyOffPossExcludingTakeFouls":2,"Assisted2sPct":1.0,"NonPutbacksAssisted2sPct":1.0,"Fg2Pct":1.0,"PenaltyFg2Pct":1.0,"EfgPct":1.0,"PenaltyEfgPct":1.0,"TsPct":1.0,"PenaltyTsPct":1.0,"Pace":125.21739130434781,"SecondsPerPossOff":9.0,"SecondsPerPossDef":14.0,"SecondsExcludingORebsPerPossOff":9.0,"SecondsExcludingORebsPerPossDef":14.0,"AtRimFrequency":1.0,"AtRimAccuracy":1.0,"UnblockedAtRimAccuracy":1.0,"AtRimPctAssisted":1.0,"PenaltyAtRimFrequency":1.0,"PenaltyAtRimAccuracy":1.0,"AtRimFG3AFrequency":1.0,"ShotQualityAvg":0.5488,"PenaltyShotQualityAvg":0.5488,"ShootingFoulsDrawnPct":0.5,"ThreePtShootingFoulsDrawnPct":1.0,"PenaltyPointsPct":1.0,"PenaltyOffPossPct":1.0},{"EntityId":"101112-2202-2405-255-959","TeamId":"1610612756","Name":"Channing Frye, Jason Richardson, Amar'e Stoudemire, Grant Hill, Steve Nash","ShortName":"Frye, Richardson, Stoudemire, Hill, Nash","RowId":"101112-2202-2405-255-959","TeamAbbreviation":"PHX","SecondsPlayed":261.0,"GamesPlayed":1,"Minutes":4,"OffPoss":9,"DefPoss":8,"PenaltyOffPoss":2,"PenaltyDefPoss":1,"SecondChanceOffPoss":1,"TotalPoss":17,"LongMidRangeFGM":3,"LongMidRangeFGA":5,"Corner3FGM":1,"Corner3FGA":1,"Arc3FGA":1,"FG2M":3,"FG2A":5,"FG3M":1,"FG3A":2,"FtPoints":2,"Points":11,"OpponentPoints":11,"SecondChanceFG2M":1,"SecondChanceFG2A":1,"SecondChancePoints":2,"PenaltyFtPoints":1,"PenaltyPoints":1,"PtsAssisted2s":4,"PtsUnassisted2s":2,"PtsAssisted3s":3,"NonHeaveArc3FGA":1,"TwoPtAssists":2,"ThreePtAssists":1,"Assists":3,"Corner3Assists":1,"LongMidRangeAssists":2,"AssistPoints":7,"OffTwoPtRebounds":1,"DefTwoPtRebounds":2,"DefRebounds":2,"OffRebounds":1,"Rebounds":3,"Steals":1,"LostBallSteals":1,"DeadBallTurnovers":2,"Turnovers":2,"PenaltyTurnovers":1,"ShootingFouls":1,"Fouls":2,"Offensive Fouls":1,"FoulsDrawn":2,"FTA":4,"TwoPtShootingFoulsDrawn":2,"FirstChancePoints":9,"PenaltyPointsExcludingTakeFouls":1,"PenaltyOffPossExcludingTakeFouls":2,"Assisted2sPct":0.6666666666666666,"NonPutbacksAssisted2sPct":0.6666666666666666,"Assisted3sPct":1.0,"Fg3Pct":0.5,"NonHeaveFg3Pct":0.5,"Fg2Pct":0.6,"SecondChanceFg2Pct":1.0,"EfgPct":0.6428571428571429,"SecondChanceEfgPct":1.0,"TsPct":0.6111111111111112,"SecondChanceTsPct":1.0,"PenaltyTsPct":0.5,"FG3APct":0.2857142857142857,"DefTwoPtReboundPct":1.0,"OffTwoPtReboundPct":0.5,"DefFGReboundPct":1.0,"OffFGReboundPct":0.3333333333333333,"OffLongMidRangeReboundPct":0.5,"DefAtRimReboundPct":1.0,"DefLongMidRangeReboundPct":1.0,"Pace":93.79310344827587,"SecondsPerPossOff":15.666666666666666,"SecondsPerPossDef":15.0,"SecondsExcludingORebsPerPossOff":14.777777777777779,"SecondsExcludingORebsPerPossDef":15.0,"LongMidRangeFrequency":0.7142857142857143,"LongMidRangeAccuracy":0.6,"UnblockedLongMidRangeAccuracy":0.6,"LongMidRangePctAssisted":0.6666666666666666,"Corner3Frequency":0.14285714285714285,"Corner3Accuracy":1.0,"UnblockedCorner3Accuracy":1.0,"Corner3PctAssisted":1.0,"Arc3Frequency":0.14285714285714285,"AtRimFG3AFrequency":0.2857142857142857,"ShotQualityAvg":0.4617071428571428,"SecondChanceShotQualityAvg":0.4167,"ShootingFoulsDrawnPct":0.2222222222222222,"TwoPtShootingFoulsDrawnPct":0.2857142857142857,"SecondChancePointsPct":0.18181818181818182,"PenaltyPointsPct":0.09090909090909091,"Avg2ptShotDistance":17.32,"Avg3ptShotDistance":25.45,"PenaltyOffPossPct":0.2222222222222222},{"EntityId":"200811-201577-201609-255-2571","TeamId":"1610612756","Name":"Lou Amundson, Robin Lopez, Goran Dragic, Grant Hill, Leandro Barbosa","ShortName":"Amundson, Lopez, Dragic, Hill, Barbosa","RowId":"200811-201577-201609-255-2571","TeamAbbreviation":"PHX","SecondsPlayed":110.0,"GamesPlayed":1,"Minutes":2,"PlusMinus":-1,"OffPoss":4,"DefPoss":3,"SecondChanceOffPoss":1,"TotalPoss":7,"AtRimFGA":1,"LongMidRangeFGM":1,"LongMidRangeFGA":1,"Arc3FGA":1,"FG2M":1,"FG2A":2,"FG3A":1,"FtPoints":2,"Points":4,"OpponentPoints":5,"SecondChanceFtPoints":2,"SecondChancePoints":2,"PtsAssisted2s":2,"NonHeaveArc3FGA":1,"TwoPtAssists":1,"Assists":1,"LongMidRangeAssists":1,"AssistPoints":2,"OffThreePtRebounds":1,"DefTwoPtRebounds":1,"DefRebounds":1,"OffRebounds":1,"Rebounds":2,"FoulsDrawn":1,"FTA":2,"TwoPtShootingFoulsDrawn":1,"FirstChancePoints":2,"Assisted2sPct":1.0,"NonPutbacksAssisted2sPct":1.0,"Fg2Pct":0.5,"EfgPct":0.3333333333333333,"TsPct":0.5,"SecondChanceTsPct":1.0,"FG3APct":0.3333333333333333,"DefTwoPtReboundPct":1.0,"OffThreePtReboundPct":1.0,"DefFGReboundPct":1.0,"OffFGReboundPct":0.5,"OffArc3ReboundPct":1.0,"DefShortMidRangeReboundPct":1.0,"Pace":91.63636363636364,"SecondsPerPossOff":15.5,"SecondsPerPossDef":16.0,"SecondsExcludingORebsPerPossOff":13.25,"SecondsExcludingORebsPerPossDef":16.0,"AtRimFrequency":0.3333333333333333,"LongMidRangeFrequency":0.3333333333333333,"LongMidRangeAccuracy":1.0,"UnblockedLongMidRangeAccuracy":1.0,"LongMidRangePctAssisted":1.0,"Arc3Frequency":0.3333333333333333,"AtRimFG3AFrequency":0.6666666666666666,"ShotQualityAvg":0.5073166666666666,"ShootingFoulsDrawnPct":0.25,"TwoPtShootingFoulsDrawnPct":0.3333333333333333,"SecondChancePointsPct":0.5,"Avg2ptShotDistance":9.35,"Avg3ptShotDistance":26.8},{"EntityId":"201577-201609-2202-2405-255","TeamId":"1610612756","Name":"Robin Lopez, Goran Dragic, Jason Richardson, Amar'e Stoudemire, Grant Hill","ShortName":"Lopez, Dragic, Richardson, Stoudemire, Hill","RowId":"201577-201609-2202-2405-255","TeamAbbreviation":"PHX","SecondsPlayed":90.0,"GamesPlayed":1,"Minutes":2,"PlusMinus":-1,"OffPoss":2,"DefPoss":2,"PenaltyOffPoss":2,"TotalPoss":4,"LongMidRangeFGM":1,"LongMidRangeFGA":2,"FG2M":1,"FG2A":2,"FtPoints":1,"Points":3,"OpponentPoints":4,"PenaltyFG2M":1,"PenaltyFG2A":2,"PenaltyFtPoints":1,"PenaltyPoints":3,"PtsAssisted2s":2,"TwoPtAssists":1,"Assists":1,"LongMidRangeAssists":1,"AssistPoints":2,"FTA":1,"Technical Free Throw Trips":1,"FirstChancePoints":3,"PenaltyPointsExcludingTakeFouls":3,"PenaltyOffPossExcludingTakeFouls":2,"Assisted2sPct":1.0,"NonPutbacksAssisted2sPct":1.0,"Fg2Pct":0.5,"PenaltyFg2Pct":0.5,"EfgPct":0.5,"PenaltyEfgPct":0.5,"TsPct":0.5,"PenaltyTsPct":0.5,"Pace":64.0,"SecondsPerPossOff":28.5,"SecondsPerPossDef":16.5,"SecondsExcludingORebsPerPossOff":28.5,"SecondsExcludingORebsPerPossDef":16.5,"LongMidRangeFrequency":1.0,"LongMidRangeAccuracy":0.5,"UnblockedLongMidRangeAccuracy":0.5,"LongMidRangePctAssisted":1.0,"ShotQualityAvg":0.37155,"PenaltyShotQualityAvg":0.37155,"PenaltyPointsPct":1.0,"Avg2ptShotDistance":17.9,"PenaltyOffPossPct":1.0},{"EntityId":"201577-2202-2405-255-959","TeamId":"1610612756","Name":"Robin Lopez, Jason Richardson, Amar'e Stoudemire, Grant Hill, Steve Nash","ShortName":"Lopez, Richardson, Stoudemire, Hill, Nash","RowId":"201577-2202-2405-255-959","TeamAbbreviation":"PHX","SecondsPlayed":798.0,"GamesPlayed":1,"Minutes":13,"PlusMinus":-1,"OffPoss":24,"DefPoss":26,"PenaltyOffPoss":6,"PenaltyDefPoss":1,"SecondChanceOffPoss":2,"TotalPoss":50,"AtRimFGM":7,"AtRimFGA":11,"SecondChanceAtRimFGM":1,"SecondChanceAtRimFGA":1,"PenaltyAtRimFGM":2,"PenaltyAtRimFGA":3,"ShortMidRangeFGM":1,"ShortMidRangeFGA":3,"LongMidRangeFGM":4,"LongMidRangeFGA":5,"Corner3FGA":1,"Arc3FGM":1,"Arc3FGA":1,"FG2M":12,"FG2A":19,"FG3M":1,"FG3A":2,"FtPoints":6,"Points":33,"OpponentPoints":34,"SecondChanceFG2M":1,"SecondChanceFG2A":1,"SecondChanceFtPoints":1,"SecondChancePoints":3,"PenaltyFG2M":2,"PenaltyFG2A":5,"PenaltyFtPoints":3,"PenaltyPoints":7,"PtsAssisted2s":18,"PtsUnassisted2s":6,"PtsAssisted3s":3,"PtsPutbacks":2,"NonHeaveArc3FGA":1,"NonHeaveArc3FGM":1,"Fg2aBlocked":1,"Fg3aBlocked":1,"TwoPtAssists":9,"ThreePtAssists":1,"Assists":10,"Arc3Assists":1,"AtRimAssists":5,"LongMidRangeAssists":4,"AssistPoints":21,"OffTwoPtRebounds":2,"DefTwoPtRebounds":9,"DefRebounds":9,"OffRebounds":2,"Rebounds":11,"Steals":1,"LostBallSteals":1,"LiveBallTurnovers":1,"BadPassOutOfBoundsTurnovers":1,"BadPassTurnovers":1,"DeadBallTurnovers":1,"Turnovers":2,"ShootingFouls":2,"Fouls":9,"Loose Ball Fouls":1,"FoulsDrawn":4,"Loose Ball Fouls Drawn":1,"FTA":7,"Technical Free Throw Trips":1,"TwoPtShootingFoulsDrawn":1,"NonShootingFoulsDrawn":2,"Blocked2s":1,"BlockedAtRim":1,"Blocks":1,"FirstChancePoints":30,"PenaltyPointsExcludingTakeFouls":7,"PenaltyOffPossExcludingTakeFouls":6,"NonShootingPenaltyNonTakeFouls":1,"NonShootingPenaltyNonTakeFoulsDrawn":2,"Assisted2sPct":0.75,"NonPutbacksAssisted2sPct":0.8181818181818182,"Assisted3sPct":1.0,"Fg3Pct":0.5,"NonHeaveFg3Pct":0.5,"Fg2Pct":0.631578947368421,"SecondChanceFg2Pct":1.0,"PenaltyFg2Pct":0.4,"EfgPct":0.6428571428571429,"SecondChanceEfgPct":1.0,"PenaltyEfgPct":0.4,"TsPct":0.6666666666666666,"SecondChanceTsPct":0.75,"PenaltyTsPct":0.5,"FG3APct":0.09523809523809523,"FG3APctBlocked":0.5,"FG2APctBlocked":0.05263157894736842,"AtRimPctBlocked":0.09090909090909091,"Corner3PctBlocked":1.0,"LiveBallTurnoverPct":0.5,"DefTwoPtReboundPct":0.75,"OffTwoPtReboundPct":0.2857142857142857,"DefFGReboundPct":0.75,"OffFGReboundPct":0.25,"OffAtRimReboundPct":0.25,"OffShortMidRangeReboundPct":0.5,"DefAtRimReboundPct":0.5,"DefShortMidRangeReboundPct":0.8,"DefLongMidRangeReboundPct":0.8,"Pace":90.22556390977444,"SecondsPerPossOff":12.833333333333334,"SecondsPerPossDef":18.846153846153847,"SecondsExcludingORebsPerPossOff":12.791666666666666,"SecondsExcludingORebsPerPossDef":18.307692307692307,"AtRimFrequency":0.5238095238095238,"AtRimAccuracy":0.6363636363636364,"UnblockedAtRimAccuracy":0.7,"AtRimPctAssisted":0.7142857142857143,"ShortMidRangeFrequency":0.14285714285714285,"ShortMidRangeAccuracy":0.3333333333333333,"UnblockedShortMidRangeAccuracy":0.3333333333333333,"LongMidRangeFrequency":0.23809523809523808,"LongMidRangeAccuracy":0.8,"UnblockedLongMidRangeAccuracy":0.8,"LongMidRangePctAssisted":1.0,"Corner3Frequency":0.047619047619047616,"Arc3Frequency":0.047619047619047616,"Arc3Accuracy":1.0,"UnblockedArc3Accuracy":1.0,"Arc3PctAssisted":1.0,"SecondChanceAtRimFrequency":1.0,"SecondChanceAtRimAccuracy":1.0,"PenaltyAtRimFrequency":0.6,"PenaltyAtRimAccuracy":0.6666666666666666,"AtRimFG3AFrequency":0.6190476190476191,"NonHeaveArc3Accuracy":1.0,"ShotQualityAvg":0.5186619047619048,"SecondChanceShotQualityAvg":0.5731,"PenaltyShotQualityAvg":0.52242,"ShootingFoulsDrawnPct":0.045454545454545456,"TwoPtShootingFoulsDrawnPct":0.05,"SecondChancePointsPct":0.09090909090909091,"PenaltyPointsPct":0.21212121212121213,"Avg2ptShotDistance":6.247368421052632,"Avg3ptShotDistance":25.2,"PenaltyOffPossPct":0.25}],"win_loss_record":null}