{"single_row_table_data":{"SecondsPlayed":2880.0,"Minutes":48,"PlusMinus":4,"OffPoss":85,"DefPoss":84,"PenaltyOffPoss":27,"PenaltyDefPoss":37,"SecondChanceOffPoss":10,"TotalPoss":169,"AtRimFGM":15,"AtRimFGA":26,"SecondChanceAtRimFGM":4,"SecondChanceAtRimFGA":6,"PenaltyAtRimFGM":6,"PenaltyAtRimFGA":7,"ShortMidRangeFGM":9,"ShortMidRangeFGA":15,"LongMidRangeFGM":11,"LongMidRangeFGA":26,"Corner3FGA":1,"PenaltyCorner3FGA":1,"Arc3FGM":5,"Arc3FGA":10,"SecondChanceArc3FGM":1,"SecondChanceArc3FGA":2,"PenaltyArc3FGM":3,"PenaltyArc3FGA":7,"FG2M":35,"FG2A":67,"FG3M":5,"FG3A":11,"FtPoints":18,"Points":103,"OpponentPoints":99,"SecondChanceFG2M":5,"SecondChanceFG2A":10,"SecondChanceFG3M":1,"SecondChanceFG3A":2,"SecondChanceFtPoints":4,"SecondChancePoints":17,"PenaltyFG2M":8,"PenaltyFG2A":20,"PenaltyFG3M":3,"PenaltyFG3A":8,"PenaltyFtPoints":6,"PenaltyPoints":31,"PtsAssisted2s":46,"PtsUnassisted2s":24,"PtsAssisted3s":15,"PtsPutbacks":4,"NonHeaveArc3FGA":10,"NonHeaveArc3FGM":5,"Fg2aBlocked":7,"TwoPtAssists":23,"ThreePtAssists":5,"Assists":28,"Arc3Assists":5,"AtRimAssists":10,"ShortMidRangeAssists":4,"LongMidRangeAssists":9,"AssistPoints":61,"OffThreePtRebounds":5,"OffTwoPtRebounds":9,"DefThreePtRebounds":7,"DefTwoPtRebounds":20,"FTDefRebounds":3,"DefRebounds":30,"OffRebounds":14,"Rebounds":44,"SelfOReb":2,"Steals":4,"LostBallSteals":4,"LiveBallTurnovers":7,"BadPassTurnovers":5,"DeadBallTurnovers":3,"LostBallOutOfBoundsTurnovers":1,"LostBallTurnovers":2,"Turnovers":10,"PenaltyTurnovers":3,"ShootingFouls":11,"Fouls":25,"Loose Ball Fouls":1,"FoulsDrawn":20,"Loose Ball Fouls Drawn":1,"Offensive Fouls Drawn":1,"FTA":24,"2pt And 1 Free Throw Trips":2,"TwoPtShootingFoulsDrawn":10,"NonShootingFoulsDrawn":3,"Blocked2s":2,"BlockedAtRim":1,"BlockedShortMidRange":1,"Blocks":2,"RecoveredBlocks":2,"DefensiveGoaltends":1,"3SecondViolations":1,"FirstChancePoints":86,"PenaltyPointsExcludingTakeFouls":31,"PenaltyOffPossExcludingTakeFouls":27,"NonShootingPenaltyNonTakeFouls":6,"NonShootingPenaltyNonTakeFoulsDrawn":3,"Assisted2sPct":0.6571428571428571,"NonPutbacksAssisted2sPct":0.696969696969697,"Assisted3sPct":1.0,"Fg3Pct":0.45454545454545453,"SecondChanceFg3Pct":0.5,"PenaltyFg3Pct":0.375,"NonHeaveFg3Pct":0.45454545454545453,"Fg2Pct":0.5223880597014925,"SecondChanceFg2Pct":0.5,"PenaltyFg2Pct":0.4,"EfgPct":0.5448717948717948,"SecondChanceEfgPct":0.5416666666666666,"PenaltyEfgPct":0.44642857142857145,"TsPct":0.5786516853932584,"SecondChanceTsPct":0.6071428571428571,"PenaltyTsPct":0.5,"FG3APct":0.14102564102564102,"FG2APctBlocked":0.1044776119402985,"AtRimPctBlocked":0.19230769230769232,"ShortMidRangePctBlocked":0.06666666666666667,"LongMidRangePctBlocked":0.038461538461538464,"LiveBallTurnoverPct":0.7,"DefFTReboundPct":0.6,"DefTwoPtReboundPct":0.8333333333333334,"OffTwoPtReboundPct":0.2903225806451613,"DefThreePtReboundPct":0.5384615384615384,"OffThreePtReboundPct":0.8333333333333334,"DefFGReboundPct":0.7297297297297297,"OffFGReboundPct":0.3783783783783784,"OffAtRimReboundPct":0.36363636363636365,"OffShortMidRangeReboundPct":0.4,"OffLongMidRangeReboundPct":0.2,"OffArc3ReboundPct":0.8,"OffCorner3ReboundPct":1.0,"DefAtRimReboundPct":0.5,"DefShortMidRangeReboundPct":0.9090909090909091,"DefLongMidRangeReboundPct":0.8888888888888888,"DefArc3ReboundPct":0.45454545454545453,"DefCorner3ReboundPct":1.0,"SelfORebPct":0.06666666666666667,"Pace":84.5,"BlocksRecoveredPct":1.0,"SecondsPerPossOff":16.564705882352943,"SecondsPerPossDef":17.523809523809526,"SecondsExcludingORebsPerPossOff":15.564705882352941,"SecondsExcludingORebsPerPossDef":16.61904761904762,"AtRimFrequency":0.3333333333333333,"AtRimAccuracy":0.5769230769230769,"UnblockedAtRimAccuracy":0.7142857142857143,"AtRimPctAssisted":0.6666666666666666,"ShortMidRangeFrequency":0.19230769230769232,"ShortMidRangeAccuracy":0.6,"UnblockedShortMidRangeAccuracy":0.6428571428571429,"ShortMidRangePctAssisted":0.4444444444444444,"LongMidRangeFrequency":0.3333333333333333,"LongMidRangeAccuracy":0.4230769230769231,"UnblockedLongMidRangeAccuracy":0.44,"LongMidRangePctAssisted":0.8181818181818182,"Corner3Frequency":0.01282051282051282,"Arc3Frequency":0.1282051282051282,"Arc3Accuracy":0.5,"UnblockedArc3Accuracy":0.5,"Arc3PctAssisted":1.0,"SecondChanceAtRimFrequency":0.5,"SecondChanceAtRimAccuracy":0.6666666666666666,"SecondChanceAtRimPctAssisted":0.25,"SecondChanceArc3Frequency":0.16666666666666666,"SecondChanceArc3Accuracy":0.5,"SecondChanceArc3PctAssisted":1.0,"PenaltyAtRimFrequency":0.25,"PenaltyAtRimAccuracy":0.8571428571428571,"PenaltyCorner3Frequency":0.03571428571428571,"PenaltyArc3Frequency":0.25,"PenaltyArc3Accuracy":0.42857142857142855,"AtRimFG3AFrequency":0.47435897435897434,"NonHeaveArc3Accuracy":0.5,"ShotQualityAvg":0.4735705128205129,"SecondChanceShotQualityAvg":0.5350499999999999,"PenaltyShotQualityAvg":0.4632232142857142,"ShootingFoulsDrawnPct":0.11627906976744186,"TwoPtShootingFoulsDrawnPct":0.13333333333333333,"SecondChancePointsPct":0.1650485436893204,"PenaltyPointsPct":0.30097087378640774,"Avg2ptShotDistance":9.044776119402986,"Avg3ptShotDistance":25.127272727272725,"PenaltyOffPossPct":0.3176470588235294},"multi_row_table_data":[{"EntityId":"101129-101236-1503-1747-436","TeamId":"1610612745","Name":"Luther Head, Chuck Hayes, Tracy McGrady, Rafer Alston, Juwan Howard","ShortName":"Head, Hayes, McGrady, Alston, Howard","RowId":"101129-101236-1503-1747-436","TeamAbbreviation":"HOU","SecondsPlayed":62.0,"GamesPlayed":1,"Minutes":1,"OffPoss":3,"DefPoss":2,"TotalPoss":5,"AtRimFGM":1,"AtRimFGA":1,"ShortMidRangeFGA":1,"FG2M":1,"FG2A":2,"FtPoints":1,"Points":3,"OpponentPoints":3,"PtsAssisted2s":2,"TwoPtAssists":1,"Assists":1,"AtRimAssists":1,"AssistPoints":2,"DefTwoPtRebounds":1,"DefRebounds":1,"Rebounds":1,"FoulsDrawn":1,"FTA":2,"TwoPtShootingFoulsDrawn":1,"FirstChancePoints":3,"Assisted2sPct":1.0,"NonPutbacksAssisted2sPct":1.0,"Fg2Pct":0.5,"EfgPct":0.5,"TsPct":0.5,"DefTwoPtReboundPct":1.0,"DefFGReboundPct":1.0,"DefLongMidRangeReboundPct":1.0,"Pace":116.1290322580645,"SecondsPerPossOff":8.666666666666666,"SecondsPerPossDef":18.0,"SecondsExcludingORebsPerPossOff":8.666666666666666,"SecondsExcludingORebsPerPossDef":18.0,"AtRimFrequency":0.5,"AtRimAccuracy":1.0,"UnblockedAtRimAccuracy":1.0,"AtRimPctAssisted":1.0,"ShortMidRangeFrequency":0.5,"AtRimFG3AFrequency":0.5,"ShotQualityAvg":0.4867,"ShootingFoulsDrawnPct":0.3333333333333333,"TwoPtShootingFoulsDrawnPct":0.3333333333333333,"Avg2ptShotDistance":6.05},{"EntityId":"101129-1503-1747-2203-2397","TeamId":"1610612745","Name":"Luther Head, Tracy McGrady, Rafer Alston, Shane Battier, Yao Ming","ShortName":"Head, McGrady, Alston, Battier, Ming","RowId":"101129-1503-1747-2203-2397","TeamAbbreviation":"HOU","SecondsPlayed":19.0,"GamesPlayed":1,"OffPoss":1,"DefPoss":1,"PenaltyOffPoss":1,"PenaltyDefPoss":1,"TotalPoss":2,"FtPoints":2,"Points":2,"OpponentPoints":2,"PenaltyFtPoints":2,"PenaltyPoints":2,"FoulsDrawn":1,"FTA":2,"NonShootingFoulsDrawn":1,"FirstChancePoints":2,"PenaltyPointsExcludingTakeFouls":2,"PenaltyOffPossExcludingTakeFouls":1,"NonShootingPenaltyNonTakeFoulsDrawn":1,"TsPct":1.0,"PenaltyTsPct":1.0,"Pace":151.57894736842107,"SecondsPerPossOff":8.0,"SecondsPerPossDef":11.0,"SecondsExcludingORebsPerPossOff":8.0,"SecondsExcludingORebsPerPossDef":11.0,"PenaltyPointsPct":1.0,"PenaltyOffPossPct":1.0},{"EntityId":"101129-1503-1747-2397-436","TeamId":"1610612745","Name":"Luther Head, Tracy McGrady, Rafer Alston, Yao Ming, Juwan Howard","ShortName":"Head, McGrady, Alston, Ming, Howard","RowId":"101129-1503-1747-2397-436","TeamAbbreviation":"HOU","SecondsPlayed":131.0,"GamesPlayed":1,"Minutes":2,"PlusMinus":-5,"OffPoss":3,"DefPoss":4,"SecondChanceOffPoss":1,"TotalPoss":7,"AtRimFGA":1,"SecondChanceAtRimFGA":1,"ShortMidRangeFGM":1,"ShortMidRangeFGA":1,"Arc3FGA":1,"FG2M":1,"FG2A":2,"FG3A":1,"Points":2,"OpponentPoints":7,"SecondChanceFG2A":1,"PtsUnassisted2s":2,"NonHeaveArc3FGA":1,"Fg2aBlocked":1,"OffThreePtRebounds":1,"DefTwoPtRebounds":1,"DefRebounds":1,"OffRebounds":1,"Rebounds":2,"LiveBallTurnovers":1,"BadPassTurnovers":1,"Turnovers":1,"ShootingFouls":2,"Fouls":2,"FirstChancePoints":2,"Fg2Pct":0.5,"EfgPct":0.3333333333333333,"TsPct":0.3333333333333333,"FG3APct":0.3333333333333333,"FG2APctBlocked":0.5,"AtRimPctBlocked":1.0,"LiveBallTurnoverPct":1.0,"DefTwoPtReboundPct":1.0,"OffThreePtReboundPct":1.0,"DefFGReboundPct":1.0,"OffFGReboundPct":0.5,"OffArc3ReboundPct":1.0,"DefLongMidRangeReboundPct":1.0,"Pace":76.94656488549619,"SecondsPerPossOff":23.333333333333332,"SecondsPerPossDef":15.25,"SecondsExcludingORebsPerPossOff":22.333333333333332,"SecondsExcludingORebsPerPossDef":13.5,"AtRimFrequency":0.3333333333333333,"ShortMidRangeFrequency":0.3333333333333333,"ShortMidRangeAccuracy":1.0,"UnblockedShortMidRangeAccuracy":1.0,"Arc3Frequency":0.3333333333333333,"SecondChanceAtRimFrequency":1.0,"AtRimFG3AFrequency":0.6666666666666666,"ShotQualityAvg":0.5035666666666666,"Avg2ptShotDistance":2.5,"Avg3ptShotDistance":24.9},{"EntityId":"101129-1503-1747-436-87","TeamId":"1610612745","Name":"Luther Head, Tracy McGrady, Rafer Alston, Juwan Howard, Dikembe Mutombo","ShortName":"Head, McGrady, Alston, Howard, Mutombo","RowId":"101129-1503-1747-436-87","TeamAbbreviation":"HOU","SecondsPlayed":186.0,"GamesPlayed":1,"Minutes":3,"PlusMinus":-1,"OffPoss":6,"DefPoss":7,"PenaltyOffPoss":6,"PenaltyDefPoss":4,"SecondChanceOffPoss":1,"TotalPoss":13,"AtRimFGM":1,"AtRimFGA":2,"PenaltyAtRimFGM":1,"PenaltyAtRimFGA":2,"LongMidRangeFGM":1,"LongMidRangeFGA":4,"Arc3FGM":1,"Arc3FGA":2,"PenaltyArc3FGM":1,"PenaltyArc3FGA":2,"FG2M":2,"FG2A":6,"FG3M":1,"FG3A":2,"Points":7,"OpponentPoints":8,"SecondChanceFG2A":2,"PenaltyFG2M":2,"PenaltyFG2A":6,"PenaltyFG3M":1,"PenaltyFG3A":2,"PenaltyPoints":7,"PtsAssisted2s":4,"PtsAssisted3s":3,"NonHeaveArc3FGA":2,"NonHeaveArc3FGM":1,"Fg2aBlocked":2,"TwoPtAssists":2,"ThreePtAssists":1,"Assists":3,"Arc3Assists":1,"AtRimAssists":1,"LongMidRangeAssists":1,"AssistPoints":7,"OffTwoPtRebounds":2,"FTDefRebounds":1,"DefRebounds":1,"OffRebounds":2,"Rebounds":3,"ShootingFouls":1,"Fouls":3,"Loose Ball Fouls":1,"FirstChancePoints":7,"PenaltyPointsExcludingTakeFouls":7,"PenaltyOffPossExcludingTakeFouls":6,"NonShootingPenaltyNonTakeFouls":1,"Assisted2sPct":1.0,"NonPutbacksAssisted2sPct":1.0,"Assisted3sPct":1.0,"Fg3Pct":0.5,"PenaltyFg3Pct":0.5,"NonHeaveFg3Pct":0.5,"Fg2Pct":0.3333333333333333,"PenaltyFg2Pct":0.3333333333333333,"EfgPct":0.4375,"PenaltyEfgPct":0.4375,"TsPct":0.4375,"PenaltyTsPct":0.4375,"FG3APct":0.25,"FG2APctBlocked":0.3333333333333333,"AtRimPctBlocked":0.5,"LongMidRangePctBlocked":0.25,"DefFTReboundPct":1.0,"OffTwoPtReboundPct":0.5,"OffFGReboundPct":0.4,"OffAtRimReboundPct":1.0,"OffLongMidRangeReboundPct":0.3333333333333333,"Pace":100.64516129032258,"SecondsPerPossOff":18.333333333333332,"SecondsPerPossDef":10.857142857142858,"SecondsExcludingORebsPerPossOff":16.666666666666668,"SecondsExcludingORebsPerPossDef":10.857142857142858,"AtRimFrequency":0.25,"AtRimAccuracy":0.5,"UnblockedAtRimAccuracy":1.0,"AtRimPctAssisted":1.0,"LongMidRangeFrequency":0.5,"LongMidRangeAccuracy":0.25,"UnblockedLongMidRangeAccuracy":0.3333333333333333,"LongMidRangePctAssisted":1.0,"Arc3Frequency":0.25,"Arc3Accuracy":0.5,"UnblockedArc3Accuracy":0.5,"Arc3PctAssisted":1.0,"PenaltyAtRimFrequency":0.25,"PenaltyAtRimAccuracy":0.5,"PenaltyArc3Frequency":0.25,"PenaltyArc3Accuracy":0.5,"AtRimFG3AFrequency":0.5,"NonHeaveArc3Accuracy":0.5,"ShotQualityAvg":0.46975,"SecondChanceShotQualityAvg":0.42485,"PenaltyShotQualityAvg":0.46975,"PenaltyPointsPct":1.0,"Avg2ptShotDistance":11.65,"Avg3ptShotDistance":25.35,"PenaltyOffPossPct":1.0},{"EntityId":"101129-1503-2203-2397-436","TeamId":"1610612745","Name":"Luther Head, Tracy McGrady, Shane Battier, Yao Ming, Juwan Howard","ShortName":"Head, McGrady, Battier, Ming, Howard","RowId":"101129-1503-2203-2397-436","TeamAbbreviation":"HOU","SecondsPlayed":174.0,"GamesPlayed":1,"Minutes":3,"PlusMinus":5,"OffPoss":5,"DefPoss":5,"TotalPoss":10,"ShortMidRangeFGM":2,"ShortMidRangeFGA":2,"LongMidRangeFGA":2,"Arc3FGM":1,"Arc3FGA":1,"FG2M":2,"FG2A":4,"FG3M":1,"FG3A":1,"Points":7,"OpponentPoints":2,"PtsAssisted2s":2,"PtsUnassisted2s":2,"PtsAssisted3s":3,"NonHeaveArc3FGA":1,"NonHeaveArc3FGM":1,"TwoPtAssists":1,"ThreePtAssists":1,"Assists":2,"Arc3Assists":1,"ShortMidRangeAssists":1,"AssistPoints":5,"DefThreePtRebounds":1,"DefTwoPtRebounds":2,"FTDefRebounds":1,"DefRebounds":4,"Rebounds":4,"Fouls":2,"FoulsDrawn":1,"FirstChancePoints":7,"Assisted2sPct":0.5,"NonPutbacksAssisted2sPct":0.5,"Assisted3sPct":1.0,"Fg3Pct":1.0,"NonHeaveFg3Pct":1.0,"Fg2Pct":0.5,"EfgPct":0.7,"TsPct":0.7,"FG3APct":0.2,"DefFTReboundPct":1.0,"DefTwoPtReboundPct":1.0,"DefThreePtReboundPct":1.0,"DefFGReboundPct":1.0,"DefShortMidRangeReboundPct":1.0,"DefArc3ReboundPct":1.0,"Pace":82.75862068965517,"SecondsPerPossOff":17.4,"SecondsPerPossDef":17.4,"SecondsExcludingORebsPerPossOff":17.4,"SecondsExcludingORebsPerPossDef":17.4,"ShortMidRangeFrequency":0.4,"ShortMidRangeAccuracy":1.0,"UnblockedShortMidRangeAccuracy":1.0,"ShortMidRangePctAssisted":0.5,"LongMidRangeFrequency":0.4,"Arc3Frequency":0.2,"Arc3Accuracy":1.0,"UnblockedArc3Accuracy":1.0,"Arc3PctAssisted":1.0,"AtRimFG3AFrequency":0.2,"NonHeaveArc3Accuracy":1.0,"ShotQualityAvg":0.41241000000000005,"Avg2ptShotDistance":14.05,"Avg3ptShotDistance":26.0},{"EntityId":"101129-1747-2203-2397-436","TeamId":"1610612745","Name":"Luther Head, Rafer Alston, Shane Battier, Yao Ming, Juwan Howard","ShortName":"Head, Alston, Battier, Ming, Howard","RowId":"101129-1747-2203-2397-436","TeamAbbreviation":"HOU","SecondsPlayed":370.0,"GamesPlayed":1,"Minutes":6,"PlusMinus":-3,"OffPoss":12,"DefPoss":10,"PenaltyOffPoss":6,"PenaltyDefPoss":6,"SecondChanceOffPoss":2,"TotalPoss":22,"AtRimFGM":3,"AtRimFGA":6,"SecondChanceAtRimFGM":2,"SecondChanceAtRimFGA":3,"PenaltyAtRimFGM":2,"PenaltyAtRimFGA":2,"ShortMidRangeFGM":1,"ShortMidRangeFGA":4,"LongMidRangeFGM":1,"LongMidRangeFGA":4,"FG2M":5,"FG2A":14,"FtPoints":1,"Points":11,"OpponentPoints":14,"SecondChanceFG2M":2,"SecondChanceFG2A":4,"SecondChanceFtPoints":1,"SecondChancePoints":5,"PenaltyFG2M":2,"PenaltyFG2A":6,"PenaltyPoints":4,"PtsAssisted2s":2,"PtsUnassisted2s":8,"PtsPutbacks":2,"TwoPtAssists":1,"Assists":1,"AtRimAssists":1,"AssistPoints":2,"OffTwoPtRebounds":4,"DefThreePtRebounds":1,"DefTwoPtRebounds":1,"DefRebounds":2,"OffRebounds":4,"Rebounds":6,"SelfOReb":2,"LiveBallTurnovers":2,"BadPassTurnovers":1,"LostBallTurnovers":1,"Turnovers":2,"PenaltyTurnovers":1,"ShootingFouls":2,"Fouls":8,"FoulsDrawn":3,"Offensive Fouls Drawn":1,"FTA":1,"2pt And 1 Free Throw Trips":1,"TwoPtShootingFoulsDrawn":1,"FirstChancePoints":6,"PenaltyPointsExcludingTakeFouls":4,"PenaltyOffPossExcludingTakeFouls":6,"NonShootingPenaltyNonTakeFouls":4,"Assisted2sPct":0.2,"NonPutbacksAssisted2sPct":0.25,"Fg2Pct":0.35714285714285715,"SecondChanceFg2Pct":0.5,"PenaltyFg2Pct":0.3333333333333333,"EfgPct":0.35714285714285715,"SecondChanceEfgPct":0.5,"PenaltyEfgPct":0.3333333333333333,"TsPct":0.39285714285714285,"SecondChanceTsPct":0.625,"PenaltyTsPct":0.3333333333333333,"LiveBallTurnoverPct":1.0,"DefTwoPtReboundPct":0.5,"OffTwoPtReboundPct":0.5,"DefThreePtReboundPct":0.5,"DefFGReboundPct":0.5,"OffFGReboundPct":0.5,"OffAtRimReboundPct":0.3333333333333333,"OffShortMidRangeReboundPct":1.0,"OffLongMidRangeReboundPct":0.3333333333333333,"DefShortMidRangeReboundPct":1.0,"DefArc3ReboundPct":0.5,"SelfORebPct":0.25,"Pace":85.62162162162161,"SecondsPerPossOff":17.0,"SecondsPerPossDef":16.6,"SecondsExcludingORebsPerPossOff":15.25,"SecondsExcludingORebsPerPossDef":16.5,"AtRimFrequency":0.42857142857142855,"AtRimAccuracy":0.5,"UnblockedAtRimAccuracy":0.5,"AtRimPctAssisted":0.3333333333333333,"ShortMidRangeFrequency":0.2857142857142857,"ShortMidRangeAccuracy":0.25,"UnblockedShortMidRangeAccuracy":0.25,"LongMidRangeFrequency":0.2857142857142857,"LongMidRangeAccuracy":0.25,"UnblockedLongMidRangeAccuracy":0.25,"SecondChanceAtRimFrequency":0.75,"SecondChanceAtRimAccuracy":0.6666666666666666,"PenaltyAtRimFrequency":0.3333333333333333,"PenaltyAtRimAccuracy":1.0,"AtRimFG3AFrequency":0.42857142857142855,"ShotQualityAvg":0.4762571428571429,"SecondChanceShotQualityAvg":0.58685,"PenaltyShotQualityAvg":0.44455,"ShootingFoulsDrawnPct":0.07142857142857142,"TwoPtShootingFoulsDrawnPct":0.07142857142857142,"SecondChancePointsPct":0.45454545454545453,"PenaltyPointsPct":0.36363636363636365,"Avg2ptShotDistance":8.55,"PenaltyOffPossPct":0.5},{"EntityId":"101236-1503-1747-2203-2397","TeamId":"1610612745","Name":"Chuck Hayes, Tracy McGrady, Rafer Alston, Shane Battier, Yao Ming","ShortName":"Hayes, McGrady, Alston, Battier, Ming","RowId":"101236-1503-1747-2203-2397","TeamAbbreviation":"HOU","SecondsPlayed":1236.0,"GamesPlayed":1,"Minutes":21,"PlusMinus":10,"OffPoss":36,"DefPoss":35,"PenaltyOffPoss":6,"PenaltyDefPoss":6,"SecondChanceOffPoss":4,"TotalPoss":71,"AtRimFGM":4,"AtRimFGA":7,"PenaltyAtRimFGM":1,"PenaltyAtRimFGA":1,"ShortMidRangeFGM":4,"ShortMidRangeFGA":4,"LongMidRangeFGM":9,"LongMidRangeFGA":14,"Corner3FGA":1,"PenaltyCorner3FGA":1,"Arc3FGM":2,"Arc3FGA":4,"SecondChanceArc3FGM":1,"SecondChanceArc3FGA":2,"PenaltyArc3FGM":2,"PenaltyArc3FGA":4,"FG2M":17,"FG2A":25,"FG3M":2,"FG3A":5,"FtPoints":10,"Points":50,"OpponentPoints":40,"SecondChanceFG2M":1,"SecondChanceFG2A":1,"SecondChanceFG3M":1,"SecondChanceFG3A":2,"SecondChanceFtPoints":3,"SecondChancePoints":8,"PenaltyFG2M":1,"PenaltyFG2A":2,"PenaltyFG3M":2,"PenaltyFG3A":5,"PenaltyFtPoints":2,"PenaltyPoints":10,"PtsAssisted2s":26,"PtsUnassisted2s":8,"PtsAssisted3s":6,"NonHeaveArc3FGA":4,"NonHeaveArc3FGM":2,"Fg2aBlocked":2,"TwoPtAssists":13,"ThreePtAssists":2,"Assists":15,"Arc3Assists":2,"AtRimAssists":2,"ShortMidRangeAssists":3,"LongMidRangeAssists":8,"AssistPoints":32,"OffThreePtRebounds":3,"OffTwoPtRebounds":2,"DefThreePtRebounds":4,"DefTwoPtRebounds":8,"DefRebounds":12,"OffRebounds":5,"Rebounds":17,"Steals":2,"LostBallSteals":2,"LiveBallTurnovers":2,"BadPassTurnovers":2,"DeadBallTurnovers":2,"Turnovers":4,"PenaltyTurnovers":1,"ShootingFouls":4,"Fouls":6,"FoulsDrawn":8,"Loose Ball Fouls Drawn":1,"FTA":14,"TwoPtShootingFoulsDrawn":6,"NonShootingFoulsDrawn":1,"Blocked2s":1,"BlockedAtRim":1,"Blocks":1,"RecoveredBlocks":1,"3SecondViolations":1,"FirstChancePoints":42,"PenaltyPointsExcludingTakeFouls":10,"PenaltyOffPossExcludingTakeFouls":6,"NonShootingPenaltyNonTakeFoulsDrawn":1,"Assisted2sPct":0.7647058823529411,"NonPutbacksAssisted2sPct":0.7647058823529411,"Assisted3sPct":1.0,"Fg3Pct":0.4,"SecondChanceFg3Pct":0.5,"PenaltyFg3Pct":0.4,"NonHeaveFg3Pct":0.4,"Fg2Pct":0.68,"SecondChanceFg2Pct":1.0,"PenaltyFg2Pct":0.5,"EfgPct":0.6666666666666666,"SecondChanceEfgPct":0.8333333333333334,"PenaltyEfgPct":0.5714285714285714,"TsPct":0.6756756756756757,"SecondChanceTsPct":0.8,"PenaltyTsPct":0.625,"FG3APct":0.16666666666666666,"FG2APctBlocked":0.08,"AtRimPctBlocked":0.2857142857142857,"LiveBallTurnoverPct":0.5,"DefTwoPtReboundPct":0.8888888888888888,"OffTwoPtReboundPct":0.25,"DefThreePtReboundPct":1.0,"OffThreePtReboundPct":1.0,"DefFGReboundPct":0.9230769230769231,"OffFGReboundPct":0.45454545454545453,"OffAtRimReboundPct":0.3333333333333333,"OffLongMidRangeReboundPct":0.2,"OffArc3ReboundPct":1.0,"OffCorner3ReboundPct":1.0,"DefAtRimReboundPct":0.5,"DefShortMidRangeReboundPct":1.0,"DefLongMidRangeReboundPct":1.0,"DefArc3ReboundPct":1.0,"DefCorner3ReboundPct":1.0,"Pace":82.71844660194174,"BlocksRecoveredPct":1.0,"SecondsPerPossOff":16.88888888888889,"SecondsPerPossDef":17.942857142857143,"SecondsExcludingORebsPerPossOff":15.63888888888889,"SecondsExcludingORebsPerPossDef":17.914285714285715,"AtRimFrequency":0.23333333333333334,"AtRimAccuracy":0.5714285714285714,"UnblockedAtRimAccuracy":0.8,"AtRimPctAssisted":0.5,"ShortMidRangeFrequency":0.13333333333333333,"ShortMidRangeAccuracy":1.0,"UnblockedShortMidRangeAccuracy":1.0,"ShortMidRangePctAssisted":0.75,"LongMidRangeFrequency":0.4666666666666667,"LongMidRangeAccuracy":0.6428571428571429,"UnblockedLongMidRangeAccuracy":0.6428571428571429,"LongMidRangePctAssisted":0.8888888888888888,"Corner3Frequency":0.03333333333333333,"Arc3Frequency":0.13333333333333333,"Arc3Accuracy":0.5,"UnblockedArc3Accuracy":0.5,"Arc3PctAssisted":1.0,"SecondChanceArc3Frequency":0.6666666666666666,"SecondChanceArc3Accuracy":0.5,"SecondChanceArc3PctAssisted":1.0,"PenaltyAtRimFrequency":0.14285714285714285,"PenaltyAtRimAccuracy":1.0,"PenaltyCorner3Frequency":0.14285714285714285,"PenaltyArc3Frequency":0.5714285714285714,"PenaltyArc3Accuracy":0.5,"AtRimFG3AFrequency":0.4,"NonHeaveArc3Accuracy":0.5,"ShotQualityAvg":0.46091333333333334,"SecondChanceShotQualityAvg":0.5024,"PenaltyShotQualityAvg":0.4841285714285714,"ShootingFoulsDrawnPct":0.16666666666666666,"TwoPtShootingFoulsDrawnPct":0.1935483870967742,"SecondChancePointsPct":0.16,"PenaltyPointsPct":0.2,"Avg2ptShotDistance":11.564,"Avg3ptShotDistance":24.9,"PenaltyOffPossPct":0.16666666666666666},{"EntityId":"101236-1503-1747-2203-436","TeamId":"1610612745","Name":"Chuck Hayes, Tracy McGrady, Rafer Alston, Shane Battier, Juwan Howard","ShortName":"Hayes, McGrady, Alston, Battier, Howard","RowId":"101236-1503-1747-2203-436","TeamAbbreviation":"HOU","SecondsPlayed":384.0,"GamesPlayed":1,"Minutes":6,"PlusMinus":-1,"OffPoss":9,"DefPoss":10,"PenaltyOffPoss":2,"PenaltyDefPoss":10,"SecondChanceOffPoss":1,"TotalPoss":19,"AtRimFGM":4,"AtRimFGA":4,"SecondChanceAtRimFGM":1,"SecondChanceAtRimFGA":1,"ShortMidRangeFGA":1,"LongMidRangeFGA":1,"Arc3FGM":1,"Arc3FGA":1,"FG2M":4,"FG2A":6,"FG3M":1,"FG3A":1,"FtPoints":1,"Points":12,"OpponentPoints":13,"SecondChanceFG2M":1,"SecondChanceFG2A":1,"SecondChancePoints":2,"PenaltyFG2A":2,"PtsAssisted2s":8,"PtsAssisted3s":3,"NonHeaveArc3FGA":1,"NonHeaveArc3FGM":1,"TwoPtAssists":4,"ThreePtAssists":1,"Assists":5,"Arc3Assists":1,"AtRimAssists":4,"AssistPoints":11,"DefThreePtRebounds":1,"DefTwoPtRebounds":4,"DefRebounds":5,"Rebounds":5,"Steals":1,"LostBallSteals":1,"LiveBallTurnovers":2,"BadPassTurnovers":1,"LostBallTurnovers":1,"Turnovers":2,"ShootingFouls":1,"Fouls":3,"FoulsDrawn":4,"FTA":1,"2pt And 1 Free Throw Trips":1,"TwoPtShootingFoulsDrawn":1,"FirstChancePoints":10,"PenaltyOffPossExcludingTakeFouls":2,"NonShootingPenaltyNonTakeFouls":1,"Assisted2sPct":1.0,"NonPutbacksAssisted2sPct":1.0,"Assisted3sPct":1.0,"Fg3Pct":1.0,"NonHeaveFg3Pct":1.0,"Fg2Pct":0.6666666666666666,"SecondChanceFg2Pct":1.0,"EfgPct":0.7857142857142857,"SecondChanceEfgPct":1.0,"TsPct":0.8571428571428571,"SecondChanceTsPct":1.0,"FG3APct":0.14285714285714285,"LiveBallTurnoverPct":1.0,"DefTwoPtReboundPct":1.0,"DefThreePtReboundPct":0.3333333333333333,"DefFGReboundPct":0.7142857142857143,"DefAtRimReboundPct":1.0,"DefShortMidRangeReboundPct":1.0,"DefLongMidRangeReboundPct":1.0,"DefCorner3ReboundPct":1.0,"Pace":71.25,"SecondsPerPossOff":17.555555555555557,"SecondsPerPossDef":22.6,"SecondsExcludingORebsPerPossOff":17.11111111111111,"SecondsExcludingORebsPerPossDef":18.2,"AtRimFrequency":0.5714285714285714,"AtRimAccuracy":1.0,"UnblockedAtRimAccuracy":1.0,"AtRimPctAssisted":1.0,"ShortMidRangeFrequency":0.14285714285714285,"LongMidRangeFrequency":0.14285714285714285,"Arc3Frequency":0.14285714285714285,"Arc3Accuracy":1.0,"UnblockedArc3Accuracy":1.0,"Arc3PctAssisted":1.0,"SecondChanceAtRimFrequency":1.0,"SecondChanceAtRimAccuracy":1.0,"SecondChanceAtRimPctAssisted":1.0,"AtRimFG3AFrequency":0.7142857142857143,"NonHeaveArc3Accuracy":1.0,"ShotQualityAvg":0.5075999999999999,"SecondChanceShotQualityAvg":0.5809,"PenaltyShotQualityAvg":0.3984,"ShootingFoulsDrawnPct":0.14285714285714285,"TwoPtShootingFoulsDrawnPct":0.16666666666666666,"SecondChancePointsPct":0.16666666666666666,"Avg2ptShotDistance":4.216666666666667,"Avg3ptShotDistance":25.1,"PenaltyOffPossPct":0.2222222222222222},{"EntityId":"1503-1747-2203-2397-436","TeamId":"1610612745","Name":"Tracy McGrady, Rafer Alston, Shane Battier, Yao Ming, Juwan Howard","ShortName":"McGrady, Alston, Battier, Ming, Howard","RowId":"1503-1747-2203-2397-436","TeamAbbreviation":"HOU","SecondsPlayed":318.0,"GamesPlayed":1,"Minutes":5,"PlusMinus":-1,"OffPoss":10,"DefPoss":10,"PenaltyOffPoss":6,"PenaltyDefPoss":10,"SecondChanceOffPoss":1,"TotalPoss":20,"AtRimFGM":2,"AtRimFGA":5,"SecondChanceAtRimFGM":1,"SecondChanceAtRimFGA":1,"PenaltyAtRimFGM":2,"PenaltyAtRimFGA":2,"ShortMidRangeFGM":1,"ShortMidRangeFGA":2,"LongMidRangeFGA":1,"Arc3FGA":1,"PenaltyArc3FGA":1,"FG2M":3,"FG2A":8,"FG3A":1,"FtPoints":3,"Points":9,"OpponentPoints":10,"SecondChanceFG2M":1,"SecondChanceFG2A":1,"SecondChancePoints":2,"PenaltyFG2M":3,"PenaltyFG2A":4,"PenaltyFG3A":1,"PenaltyFtPoints":2,"PenaltyPoints":8,"PtsAssisted2s":2,"PtsUnassisted2s":4,"PtsPutbacks":2,"NonHeaveArc3FGA":1,"Fg2aBlocked":2,"TwoPtAssists":1,"Assists":1,"AtRimAssists":1,"AssistPoints":2,"OffThreePtRebounds":1,"OffTwoPtRebounds":1,"DefTwoPtRebounds":3,"FTDefRebounds":1,"DefRebounds":4,"OffRebounds":2,"Rebounds":6,"Steals":1,"LostBallSteals":1,"DeadBallTurnovers":1,"LostBallOutOfBoundsTurnovers":1,"Turnovers":1,"PenaltyTurnovers":1,"ShootingFouls":1,"Fouls":1,"FoulsDrawn":2,"FTA":4,"TwoPtShootingFoulsDrawn":1,"NonShootingFoulsDrawn":1,"Blocked2s":1,"BlockedShortMidRange":1,"Blocks":1,"RecoveredBlocks":1,"DefensiveGoaltends":1,"FirstChancePoints":7,"PenaltyPointsExcludingTakeFouls":8,"PenaltyOffPossExcludingTakeFouls":6,"NonShootingPenaltyNonTakeFoulsDrawn":1,"Assisted2sPct":0.3333333333333333,"NonPutbacksAssisted2sPct":0.5,"Fg2Pct":0.375,"SecondChanceFg2Pct":1.0,"PenaltyFg2Pct":0.75,"EfgPct":0.3333333333333333,"SecondChanceEfgPct":1.0,"PenaltyEfgPct":0.6,"TsPct":0.4090909090909091,"SecondChanceTsPct":1.0,"PenaltyTsPct":0.6666666666666666,"FG3APct":0.1111111111111111,"FG2APctBlocked":0.25,"AtRimPctBlocked":0.2,"ShortMidRangePctBlocked":0.5,"DefFTReboundPct":1.0,"DefTwoPtReboundPct":0.75,"OffTwoPtReboundPct":0.2,"OffThreePtReboundPct":1.0,"DefFGReboundPct":0.5,"OffFGReboundPct":0.3333333333333333,"OffAtRimReboundPct":0.3333333333333333,"OffArc3ReboundPct":1.0,"DefShortMidRangeReboundPct":0.75,"Pace":90.56603773584906,"BlocksRecoveredPct":1.0,"SecondsPerPossOff":13.7,"SecondsPerPossDef":18.1,"SecondsExcludingORebsPerPossOff":13.5,"SecondsExcludingORebsPerPossDef":15.8,"AtRimFrequency":0.5555555555555556,"AtRimAccuracy":0.4,"UnblockedAtRimAccuracy":0.5,"AtRimPctAssisted":0.5,"ShortMidRangeFrequency":0.2222222222222222,"ShortMidRangeAccuracy":0.5,"UnblockedShortMidRangeAccuracy":1.0,"LongMidRangeFrequency":0.1111111111111111,"Arc3Frequency":0.1111111111111111,"SecondChanceAtRimFrequency":1.0,"SecondChanceAtRimAccuracy":1.0,"PenaltyAtRimFrequency":0.4,"PenaltyAtRimAccuracy":1.0,"PenaltyArc3Frequency":0.2,"AtRimFG3AFrequency":0.6666666666666666,"ShotQualityAvg":0.5095722222222222,"PenaltyShotQualityAvg":0.47185,"ShootingFoulsDrawnPct":0.1,"TwoPtShootingFoulsDrawnPct":0.1111111111111111,"SecondChancePointsPct":0.2222222222222222,"PenaltyPointsPct":0.8888888888888888,"Avg2ptShotDistance":3.5875,"Avg3ptShotDistance":25.2,"PenaltyOffPossPct":0.6}],"win_loss_record":null}